[
    {
        "type": "stateN",
        "backend": {
            "key": "LEFT_WHEEL_IN",
            "dbsimProps": {
                "stationName": "",
                "blockName": "IOToHost.LGControl",
                "elementName": "Data.LEFT_WHEEL_INDICATION",
                "elementType": "Integer",
                "enumMapping": {
                    "DOWN": 0,
                    "UP": 1
                }
            }
        },
        "component": {
            "debugMode": false,
            "isClickable": false,
            "position": {
                "imgWidth": "70",
                "imgHeight": "70",
                "posLeft": "48",
                "posTop": "143"
            },
            "imageProps": {
                "imageDefault": "/LGControlPanel/Light_off.png",
                "additionalImageData": {
                    "UP": "/LGControlPanel/Light_off.png",
                    "DOWN": "/LGControlPanel/Light_on.png"
                }
            },
            "clickProps": {
                "clickBoundsHeightFactor": 1,
                "clickBoundsWidthFactor": 1
            },
            "knobProps": {},
            "analogProps": {},
            "stringProps": {},
            "blinking": {
                "color": "yellow"
            },
            "logger": {
                "display": true
            }
        }
    }
]